easyland/__init__.py
easyland/command.py
easyland/daemon.py
easyland/idle.py
easyland/log.py
easyland/main.py
easyland-0.7.6.dist-info/LICENSE.txt
easyland-0.7.6.dist-info/METADATA
easyland-0.7.6.dist-info/WHEEL
easyland-0.7.6.dist-info/entry_points.txt
easyland-0.7.6.dist-info/top_level.txt
easyland-0.7.6.dist-info/RECORD
