Metadata-Version: 2.1
Name: easyland
Version: 0.7.6
Summary: A python swiss-knife to manage wayand compositors like Hyprland and Sway
Author-email: Julien Pro <contact@julienpro.com>
Project-URL: Homepage, https://github.com/juienpro/easyland
Project-URL: Issues, https://github.com/juienpro/easyland/issues
Classifier: Intended Audience :: Developers
Classifier: License :: OSI Approved :: MIT License
Classifier: Programming Language :: Python :: 3
Classifier: Programming Language :: Python :: 3.11
Classifier: Operating System :: POSIX :: Linux
Classifier: Topic :: Software Development :: Libraries
Classifier: Topic :: System :: Operating System
Classifier: Topic :: System :: Systems Administration
Classifier: Topic :: Desktop Environment
Requires-Python: >=3.11
License-File: LICENSE.txt
Requires-Dist: pywayland >=0.4.17
